{
    "planes": [
        {
            "id": 1,
            "nombre": "Plan Básico",
            "precio": 99,
            "descripcion": "Servicio básico, Soporte por email, Actualizaciones mensuales",
            "caracteristicas": [
                "Servicio básico",
                "Soporte por email",
                "Actualizaciones mensuales"
            ]
        },
        {
            "id": 2,
            "nombre": "Plan Profesional",
            "precio": 199,
            "descripcion": "Todo del plan básico, Soporte prioritario, Funciones avanzadas",
            "caracteristicas": [
                "Todo del plan básico",
                "Soporte prioritario",
                "Funciones avanzadas"
            ],
            "popular": true
        },
        {
            "id": 3,
            "nombre": "Plan Empresarial",
            "precio": 399,
            "descripcion": "Todo del plan profesional, Soporte 24/7, Funciones personalizadas",
            "caracteristicas": [
                "Todo del plan profesional",
                "Soporte 24/7",
                "Funciones personalizadas"
            ]
        }
    ],
    "configuracion": {
        "costoServicio": 25,
        "moneda": "USD",
        "impuestos": 0
    }
}
